setupmeta_builder/__init__.py
setupmeta_builder/__main__.py
setupmeta_builder/bases.py
setupmeta_builder/classifiers.py
setupmeta_builder/consts.py
setupmeta_builder/core.py
setupmeta_builder/licenses.py
setupmeta_builder/requires_resolver.py
setupmeta_builder/utils.py
setupmeta_builder/utils_poetry.py
setupmeta_builder/version_resolver.py
setupmeta_builder/cli/__init__.py
setupmeta_builder/cli/make_setup.py
setupmeta_builder/cli/print_attrs.py
setupmeta_builder/metadata_providers/__init__.py
setupmeta_builder/metadata_providers/filesystem.py
setupmeta_builder/metadata_providers/git.py
setupmeta_builder-0.2.1.dist-info/LICENSE
setupmeta_builder-0.2.1.dist-info/METADATA
setupmeta_builder-0.2.1.dist-info/WHEEL
setupmeta_builder-0.2.1.dist-info/top_level.txt
setupmeta_builder-0.2.1.dist-info/RECORD
