Metadata-Version: 2.1
Name: setupmeta-builder
Version: 0.2.1
Summary: UNKNOWN
Home-page: https://github.com/Cologler/setupmeta_builder-python
Author: Cologler
Author-email: skyoflw@gmail.com
License: MIT License
Platform: UNKNOWN
Classifier: Development Status :: 5 - Production/Stable
Classifier: License :: OSI Approved :: MIT License
Classifier: Programming Language :: Python :: 3.7
Classifier: Programming Language :: Python :: 3.8
Classifier: Programming Language :: Python :: 3.9
Requires-Dist: fsoopify
Requires-Dist: packaging
Requires-Dist: pipfile
Requires-Dist: poetry
Requires-Dist: prettyprinter
Requires-Dist: pyyaml
Requires-Dist: toml
